kivy_trio/__init__.py
kivy_trio/context.py
kivy_trio/to_kivy.py
kivy_trio/to_trio.py
kivy_trio/tests/__init__.py
kivy_trio/tests/test_context.py
kivy_trio-0.1.0.dist-info/licenses/LICENSE
kivy_trio-0.1.0.dist-info/METADATA
kivy_trio-0.1.0.dist-info/WHEEL
kivy_trio-0.1.0.dist-info/top_level.txt
kivy_trio-0.1.0.dist-info/RECORD
