Metadata-Version: 2.4
Name: kivy_trio
Version: 0.1.0
Summary: A Kivy - Trio integration and scheduling library.
Home-page: https://github.com/matham/kivy-trio
Author: Matthew Einhorn
Author-email: matt@einhorn.dev
License: MIT
Project-URL: Bug Reports, https://github.com/matham/kivy-trio/issues
Project-URL: Source, https://github.com/matham/kivy-trio
Classifier: Development Status :: 4 - Beta
Classifier: License :: OSI Approved :: MIT License
Classifier: Programming Language :: Python :: 3.7
Classifier: Programming Language :: Python :: 3.8
Classifier: Programming Language :: Python :: 3.9
Classifier: Programming Language :: Python :: 3.10
License-File: LICENSE
Requires-Dist: kivy>=2.0.0
Requires-Dist: trio
Requires-Dist: outcome
Provides-Extra: dev
Requires-Dist: pytest>=3.6; extra == "dev"
Requires-Dist: pytest-cov; extra == "dev"
Requires-Dist: sphinx-rtd-theme; extra == "dev"
Requires-Dist: coveralls; extra == "dev"
Requires-Dist: setuptools; extra == "dev"
Requires-Dist: sphinx; extra == "dev"
Requires-Dist: flake8; extra == "dev"
Requires-Dist: wheel; extra == "dev"
Requires-Dist: pytest-trio; extra == "dev"
Requires-Dist: sphinxcontrib-trio; extra == "dev"
Requires-Dist: sphinx-autodoc-typehints; extra == "dev"
Requires-Dist: pytest-kivy; extra == "dev"
Dynamic: author
Dynamic: author-email
Dynamic: classifier
Dynamic: description
Dynamic: home-page
Dynamic: license
Dynamic: license-file
Dynamic: project-url
Dynamic: summary
